[
    {
        "name": "id",
        "dbType": "integer,true,true",
        "htmlType": null,
        "validations": null,
        "searchable": false,
        "fillable": false,
        "primary": true,
        "inForm": false,
        "inIndex": false
    },
    {
        "name": "idcode",
        "dbType": "string",
        "htmlType": null,
        "validations": null,
        "searchable": true,
        "fillable": true,
        "primary": false,
        "inForm": true,
        "inIndex": true
    },
    {
        "name": "type",
        "dbType": "string",
        "htmlType": null,
        "validations": null,
        "searchable": true,
        "fillable": true,
        "primary": false,
        "inForm": true,
        "inIndex": true
    },
    {
        "name": "name",
        "dbType": "string",
        "htmlType": null,
        "validations": null,
        "searchable": true,
        "fillable": true,
        "primary": false,
        "inForm": true,
        "inIndex": true
    },
    {
        "name": "gender",
        "dbType": "string",
        "htmlType": null,
        "validations": null,
        "searchable": true,
        "fillable": true,
        "primary": false,
        "inForm": true,
        "inIndex": true
    },
    {
        "name": "nrc_id",
        "dbType": "string",
        "htmlType": null,
        "validations": null,
        "searchable": true,
        "fillable": true,
        "primary": false,
        "inForm": true,
        "inIndex": true
    },
    {
        "name": "dob",
        "dbType": "datetime",
        "htmlType": null,
        "validations": null,
        "searchable": true,
        "fillable": true,
        "primary": false,
        "inForm": true,
        "inIndex": true
    },
    {
        "name": "father",
        "dbType": "string",
        "htmlType": null,
        "validations": null,
        "searchable": true,
        "fillable": true,
        "primary": false,
        "inForm": true,
        "inIndex": true
    },
    {
        "name": "mother",
        "dbType": "string",
        "htmlType": null,
        "validations": null,
        "searchable": true,
        "fillable": true,
        "primary": false,
        "inForm": true,
        "inIndex": true
    },
    {
        "name": "address",
        "dbType": "text",
        "htmlType": null,
        "validations": null,
        "searchable": true,
        "fillable": true,
        "primary": false,
        "inForm": true,
        "inIndex": true
    },
    {
        "name": "village",
        "dbType": "string",
        "htmlType": null,
        "validations": null,
        "searchable": true,
        "fillable": true,
        "primary": false,
        "inForm": true,
        "inIndex": true
    },
    {
        "name": "village_tract",
        "dbType": "string",
        "htmlType": null,
        "validations": null,
        "searchable": true,
        "fillable": true,
        "primary": false,
        "inForm": true,
        "inIndex": true
    },
    {
        "name": "township",
        "dbType": "string",
        "htmlType": null,
        "validations": null,
        "searchable": true,
        "fillable": true,
        "primary": false,
        "inForm": true,
        "inIndex": true
    },
    {
        "name": "district",
        "dbType": "string",
        "htmlType": null,
        "validations": null,
        "searchable": true,
        "fillable": true,
        "primary": false,
        "inForm": true,
        "inIndex": true
    },
    {
        "name": "state",
        "dbType": "string",
        "htmlType": null,
        "validations": null,
        "searchable": true,
        "fillable": true,
        "primary": false,
        "inForm": true,
        "inIndex": true
    },
    {
        "name": "parent_id",
        "dbType": "integer,false,true",
        "htmlType": null,
        "validations": null,
        "searchable": true,
        "fillable": true,
        "primary": false,
        "inForm": true,
        "inIndex": true
    },
    {
        "name": "created_at",
        "dbType": "datetime",
        "htmlType": null,
        "validations": null,
        "searchable": true,
        "fillable": true,
        "primary": false,
        "inForm": true,
        "inIndex": true
    },
    {
        "name": "updated_at",
        "dbType": "datetime",
        "htmlType": null,
        "validations": null,
        "searchable": true,
        "fillable": true,
        "primary": false,
        "inForm": true,
        "inIndex": true
    }
]