[
    {
        "name": "id",
        "dbType": "increments",
        "validations": "",
        "searchable": false,
        "fillable": false,
        "primary": true,
        "inForm": false,
        "inIndex": false
    },
    {
        "name": "sectionname",
        "dbType": "string:index",
        "htmlType": "text",
        "validations": "",
        "searchable": true,
        "fillable": true,
        "primary": false,
        "inForm": false,
        "inIndex": false
    },
    {
        "name": "sort",
        "dbType": "integer:index",
        "validations": "",
        "searchable": true,
        "fillable": true,
        "primary": false,
        "inForm": false,
        "inIndex": false
    },
    {
        "name": "project_id",
        "dbType": "integer:unsigned:foreign,projects,id",
        "relation": "mt1,Project",
        "htmlType": "number",
        "validations": "",
        "searchable": true,
        "fillable": true,
        "primary": false,
        "inForm": false,
        "inIndex": false
    }
]